{
  "created_at_iso": "2026-03-13T09:55:44.071717",
  "camera": {
    "frame_width": 640,
    "frame_height": 480,
    "frame_fps": 30
  },
  "apriltag": {
    "family": "tag36h11",
    "tag_size_m": 0.04
  },
  "ros_topic": "/joint_states",
  "snapshot_count": 31,
  "snapshots": [
    {
      "saved_at_unix": 1773361063.2323465,
      "saved_at_iso": "2026-03-13T09:17:43.232347",
      "april_tags": [
        {
          "tag_id": 1,
          "position_m": {
            "x": 0.15755065943236335,
            "y": -0.09392112836532776,
            "z": 0.3865094006281904
          },
          "orientation_deg": {
            "roll": -18.840855696605427,
            "pitch": 12.609977624837743,
            "yaw": -48.428074309181575
          },
          "tracking": true
        }
      ],
      "franka_right_arm": {
        "received": true,
        "receive_count": 148848,
        "arm_id": 0,
        "joint_names": [
          "fr3_joint1",
          "fr3_joint2",
          "fr3_joint3",
          "fr3_joint4",
          "fr3_joint5",
          "fr3_joint6",
          "fr3_joint7"
        ],
        "joint_positions": [
          1.159706711769104,
          0.23201844096183777,
          -0.7319132089614868,
          -2.2370026111602783,
          1.749955177307129,
          1.1805437803268433,
          0.22334541380405426
        ],
        "joint_torques": [
          18.10795783996582,
          -5.8169636726379395,
          13.64949893951416,
          17.658344268798828,
          0.7695035934448242,
          -1.5051957368850708,
          0.09668698161840439
        ],
        "source_topic": "/joint_states",
        "source_stamp": {
          "sec": 1773361063,
          "nanosec": 230519702
        }
      }
    },
    {
      "saved_at_unix": 1773361107.9063592,
      "saved_at_iso": "2026-03-13T09:18:27.906359",
      "april_tags": [
        {
          "tag_id": 1,
          "position_m": {
            "x": 0.18569958946798448,
            "y": -0.0729125908047071,
            "z": 0.4553969845474566
          },
          "orientation_deg": {
            "roll": -31.755347879281125,
            "pitch": 10.447413318758676,
            "yaw": -48.12711233044853
          },
          "tracking": true
        }
      ],
      "franka_right_arm": {
        "received": true,
        "receive_count": 193332,
        "arm_id": 0,
        "joint_names": [
          "fr3_joint1",
          "fr3_joint2",
          "fr3_joint3",
          "fr3_joint4",
          "fr3_joint5",
          "fr3_joint6",
          "fr3_joint7"
        ],
        "joint_positions": [
          1.157670021057129,
          0.24745428562164307,
          -0.8813549280166626,
          -2.3139660358428955,
          1.7441229820251465,
          1.194618821144104,
          0.20985640585422516
        ],
        "joint_torques": [
          18.86570930480957,
          -4.4085774421691895,
          13.64949893951416,
          16.650653839111328,
          0.4362516701221466,
          -1.6837235689163208,
          0.14978757500648499
        ],
        "source_topic": "/joint_states",
        "source_stamp": {
          "sec": 1773361107,
          "nanosec": 905162612
        }
      }
    },
    {
      "saved_at_unix": 1773361142.7144783,
      "saved_at_iso": "2026-03-13T09:19:02.714478",
      "april_tags": [
        {
          "tag_id": 1,
          "position_m": {
            "x": 0.18085497476126805,
            "y": -0.07928654203616445,
            "z": 0.4997953311196253
          },
          "orientation_deg": {
            "roll": -30.342973519775274,
            "pitch": 12.007065655240561,
            "yaw": -49.28133657132231
          },
          "tracking": true
        }
      ],
      "franka_right_arm": {
        "received": true,
        "receive_count": 228000,
        "arm_id": 0,
        "joint_names": [
          "fr3_joint1",
          "fr3_joint2",
          "fr3_joint3",
          "fr3_joint4",
          "fr3_joint5",
          "fr3_joint6",
          "fr3_joint7"
        ],
        "joint_positions": [
          1.075223684310913,
          0.4524167776107788,
          -0.9019206762313843,
          -2.1840691566467285,
          1.7427083253860474,
          1.0037163496017456,
          0.1959245502948761
        ],
        "joint_torques": [
          21.42460823059082,
          -9.712837219238281,
          10.97951602935791,
          17.412372589111328,
          0.5763273239135742,
          -1.7359086275100708,
          0.17633786797523499
        ],
        "source_topic": "/joint_states",
        "source_stamp": {
          "sec": 1773361142,
          "nanosec": 713743812
        }
      }
    },
    {
      "saved_at_unix": 1773361174.9882941,
      "saved_at_iso": "2026-03-13T09:19:34.988294",
      "april_tags": [
        {
          "tag_id": 1,
          "position_m": {
            "x": 0.22573213130055902,
            "y": -0.056447155600920784,
            "z": 0.5930847366588967
          },
          "orientation_deg": {
            "roll": -21.21973777018857,
            "pitch": 29.752940304197026,
            "yaw": -34.309605211476786
          },
          "tracking": true
        }
      ],
      "franka_right_arm": {
        "received": true,
        "receive_count": 260160,
        "arm_id": 0,
        "joint_names": [
          "fr3_joint1",
          "fr3_joint2",
          "fr3_joint3",
          "fr3_joint4",
          "fr3_joint5",
          "fr3_joint6",
          "fr3_joint7"
        ],
        "joint_positions": [
          1.0302612781524658,
          0.701408326625824,
          -1.1088941097259521,
          -2.038193702697754,
          1.5705827474594116,
          0.8174402117729187,
          -0.28196677565574646
        ],
        "joint_torques": [
          24.36436653137207,
          -12.731941223144531,
          5.155540943145752,
          17.511554718017578,
          0.9965543746948242,
          -1.6306229829788208,
          0.08386959880590439
        ],
        "source_topic": "/joint_states",
        "source_stamp": {
          "sec": 1773361174,
          "nanosec": 986609103
        }
      }
    },
    {
      "saved_at_unix": 1773361300.5121331,
      "saved_at_iso": "2026-03-13T09:21:40.512133",
      "april_tags": [
        {
          "tag_id": 1,
          "position_m": {
            "x": 0.27084143713295794,
            "y": -0.04441801414803255,
            "z": 0.69000664877091
          },
          "orientation_deg": {
            "roll": -32.22880132493395,
            "pitch": 41.07232037984005,
            "yaw": -38.47828540676083
          },
          "tracking": true
        }
      ],
      "franka_right_arm": {
        "received": true,
        "receive_count": 385284,
        "arm_id": 0,
        "joint_names": [
          "fr3_joint1",
          "fr3_joint2",
          "fr3_joint3",
          "fr3_joint4",
          "fr3_joint5",
          "fr3_joint6",
          "fr3_joint7"
        ],
        "joint_positions": [
          0.892256498336792,
          0.8444514274597168,
          -1.1732617616653442,
          -1.943677544593811,
          1.5838745832443237,
          0.8779320120811462,
          -0.34996169805526733
        ],
        "joint_torques": [
          26.92723274230957,
          -16.14777374267578,
          1.6167227029800415,
          17.313190460205078,
          1.4103727340698242,
          -1.5381547212600708,
          0.05731930583715439
        ],
        "source_topic": "/joint_states",
        "source_stamp": {
          "sec": 1773361300,
          "nanosec": 510813871
        }
      }
    },
    {
      "saved_at_unix": 1773361334.5517342,
      "saved_at_iso": "2026-03-13T09:22:14.551734",
      "april_tags": [
        {
          "tag_id": 1,
          "position_m": {
            "x": 0.27865794403492106,
            "y": -0.019892718733863494,
            "z": 0.6204314556940695
          },
          "orientation_deg": {
            "roll": -28.88391070330044,
            "pitch": 38.65151185958278,
            "yaw": -39.73513122192664
          },
          "tracking": true
        }
      ],
      "franka_right_arm": {
        "received": true,
        "receive_count": 419183,
        "arm_id": 0,
        "joint_names": [
          "fr3_joint1",
          "fr3_joint2",
          "fr3_joint3",
          "fr3_joint4",
          "fr3_joint5",
          "fr3_joint6",
          "fr3_joint7"
        ],
        "joint_positions": [
          1.167732834815979,
          0.8577739000320435,
          -1.4103496074676514,
          -2.1441001892089844,
          1.5649157762527466,
          0.7354857325553894,
          -0.35662785172462463
        ],
        "joint_torques": [
          23.90812873840332,
          -9.335945129394531,
          -0.7953866124153137,
          17.067218780517578,
          1.2501554489135742,
          -1.4987870454788208,
          0.10401120036840439
        ],
        "source_topic": "/joint_states",
        "source_stamp": {
          "sec": 1773361334,
          "nanosec": 549778991
        }
      }
    },
    {
      "saved_at_unix": 1773361378.1607163,
      "saved_at_iso": "2026-03-13T09:22:58.160716",
      "april_tags": [
        {
          "tag_id": 1,
          "position_m": {
            "x": 0.21959014877224795,
            "y": 0.04461362044244724,
            "z": 0.5102469293414011
          },
          "orientation_deg": {
            "roll": -18.840750827141292,
            "pitch": 27.612507819147613,
            "yaw": -38.20595573552527
          },
          "tracking": true
        }
      ],
      "franka_right_arm": {
        "received": true,
        "receive_count": 462634,
        "arm_id": 0,
        "joint_names": [
          "fr3_joint1",
          "fr3_joint2",
          "fr3_joint3",
          "fr3_joint4",
          "fr3_joint5",
          "fr3_joint6",
          "fr3_joint7"
        ],
        "joint_positions": [
          1.5499908924102783,
          0.8382991552352905,
          -1.5192999839782715,
          -2.455812931060791,
          1.5828988552093506,
          0.6436315774917603,
          -0.3765801787376404
        ],
        "joint_torques": [
          17.37004280090332,
          -4.9878010749816895,
          -1.1048349142074585,
          16.499897003173828,
          1.2300138473510742,
          -1.7230912446975708,
          0.06372799724340439
        ],
        "source_topic": "/joint_states",
        "source_stamp": {
          "sec": 1773361378,
          "nanosec": 159968117
        }
      }
    },
    {
      "saved_at_unix": 1773361406.967925,
      "saved_at_iso": "2026-03-13T09:23:26.967925",
      "april_tags": [
        {
          "tag_id": 1,
          "position_m": {
            "x": 0.1010848634460603,
            "y": 0.05419102424887019,
            "z": 0.470664556517926
          },
          "orientation_deg": {
            "roll": -5.152774422653539,
            "pitch": 27.936021910826966,
            "yaw": -26.752100419065798
          },
          "tracking": true
        }
      ],
      "franka_right_arm": {
        "received": true,
        "receive_count": 491346,
        "arm_id": 0,
        "joint_names": [
          "fr3_joint1",
          "fr3_joint2",
          "fr3_joint3",
          "fr3_joint4",
          "fr3_joint5",
          "fr3_joint6",
          "fr3_joint7"
        ],
        "joint_positions": [
          1.5392813682556152,
          0.8825284838676453,
          -1.2141224145889282,
          -2.363933563232422,
          1.7410798072814941,
          0.6622567772865295,
          -0.5895899534225464
        ],
        "joint_torques": [
          16.40995979309082,
          -12.755744934082031,
          -1.7197641134262085,
          17.463947296142578,
          1.6511564254760742,
          -1.5711137056350708,
          0.03717770427465439
        ],
        "source_topic": "/joint_states",
        "source_stamp": {
          "sec": 1773361406,
          "nanosec": 966555398
        }
      }
    },
    {
      "saved_at_unix": 1773361432.4042041,
      "saved_at_iso": "2026-03-13T09:23:52.404204",
      "april_tags": [
        {
          "tag_id": 1,
          "position_m": {
            "x": 0.0784696072371311,
            "y": 0.059570955759823414,
            "z": 0.409901776593702
          },
          "orientation_deg": {
            "roll": 2.359841964900195,
            "pitch": 25.000325520530847,
            "yaw": -22.98400980645112
          },
          "tracking": true
        }
      ],
      "franka_right_arm": {
        "received": true,
        "receive_count": 516707,
        "arm_id": 0,
        "joint_names": [
          "fr3_joint1",
          "fr3_joint2",
          "fr3_joint3",
          "fr3_joint4",
          "fr3_joint5",
          "fr3_joint6",
          "fr3_joint7"
        ],
        "joint_positions": [
          1.6694010496139526,
          0.8301061987876892,
          -1.2070391178131104,
          -2.375570297241211,
          1.7582257986068726,
          0.6614003777503967,
          -0.6294235587120056
        ],
        "joint_torques": [
          14.45805549621582,
          -12.303474426269531,
          -1.6404184103012085,
          18.126483917236328,
          1.9514493942260742,
          -1.4914628267288208,
          0.07013668864965439
        ],
        "source_topic": "/joint_states",
        "source_stamp": {
          "sec": 1773361432,
          "nanosec": 402832404
        }
      }
    },
    {
      "saved_at_unix": 1773361459.2449174,
      "saved_at_iso": "2026-03-13T09:24:19.244917",
      "april_tags": [
        {
          "tag_id": 1,
          "position_m": {
            "x": 0.017682103777833552,
            "y": 0.12109126888929075,
            "z": 0.41295927648243846
          },
          "orientation_deg": {
            "roll": 9.168382119898329,
            "pitch": 23.243170137413074,
            "yaw": -13.014257043068737
          },
          "tracking": true
        }
      ],
      "franka_right_arm": {
        "received": true,
        "receive_count": 543473,
        "arm_id": 0,
        "joint_names": [
          "fr3_joint1",
          "fr3_joint2",
          "fr3_joint3",
          "fr3_joint4",
          "fr3_joint5",
          "fr3_joint6",
          "fr3_joint7"
        ],
        "joint_positions": [
          1.6599041223526,
          0.9423794150352478,
          -1.039706826210022,
          -2.34671950340271,
          1.758440375328064,
          0.6862209439277649,
          -0.9614101648330688
        ],
        "joint_torques": [
          12.58152961730957,
          -17.98462677001953,
          -4.052527904510498,
          17.658344268798828,
          1.9651823043823242,
          -1.4520951509475708,
          0.04450192302465439
        ],
        "source_topic": "/joint_states",
        "source_stamp": {
          "sec": 1773361459,
          "nanosec": 242416037
        }
      }
    },
    {
      "saved_at_unix": 1773361485.9146285,
      "saved_at_iso": "2026-03-13T09:24:45.914629",
      "april_tags": [
        {
          "tag_id": 1,
          "position_m": {
            "x": -0.07795141468515326,
            "y": 0.13744150252588472,
            "z": 0.4232715739343566
          },
          "orientation_deg": {
            "roll": 17.180319245986375,
            "pitch": 9.234135055998754,
            "yaw": -2.6783106448181906
          },
          "tracking": true
        }
      ],
      "franka_right_arm": {
        "received": true,
        "receive_count": 570050,
        "arm_id": 0,
        "joint_names": [
          "fr3_joint1",
          "fr3_joint2",
          "fr3_joint3",
          "fr3_joint4",
          "fr3_joint5",
          "fr3_joint6",
          "fr3_joint7"
        ],
        "joint_positions": [
          1.4555108547210693,
          1.104201078414917,
          -0.7560607194900513,
          -2.0264065265655518,
          1.759710431098938,
          0.6855067610740662,
          -1.234884262084961
        ],
        "joint_torques": [
          14.53343391418457,
          -29.09699249267578,
          -3.461402177810669,
          18.126483917236328,
          1.9514493942260742,
          -1.4127274751663208,
          0.05091061443090439
        ],
        "source_topic": "/joint_states",
        "source_stamp": {
          "sec": 1773361485,
          "nanosec": 913062063
        }
      }
    },
    {
      "saved_at_unix": 1773361614.4382029,
      "saved_at_iso": "2026-03-13T09:26:54.438203",
      "april_tags": [
        {
          "tag_id": 1,
          "position_m": {
            "x": -0.13287706268161653,
            "y": 0.11197037688551621,
            "z": 0.40934047932603096
          },
          "orientation_deg": {
            "roll": 22.793491438566026,
            "pitch": 10.325351422791456,
            "yaw": -19.06004736249174
          },
          "tracking": true
        }
      ],
      "franka_right_arm": {
        "received": true,
        "receive_count": 23207,
        "arm_id": 0,
        "joint_names": [
          "fr3_joint1",
          "fr3_joint2",
          "fr3_joint3",
          "fr3_joint4",
          "fr3_joint5",
          "fr3_joint6",
          "fr3_joint7"
        ],
        "joint_positions": [
          1.387679100036621,
          1.2159804105758667,
          -0.6920037865638733,
          -1.7345188856124878,
          1.7597397565841675,
          0.686276912689209,
          -0.8866915702819824
        ],
        "joint_torques": [
          15.92595100402832,
          -35.05585479736328,
          -3.592322587966919,
          19.237323760986328,
          2.265475273132324,
          -1.2012406587600708,
          0.10401120036840439
        ],
        "source_topic": "/joint_states",
        "source_stamp": {
          "sec": 1773361614,
          "nanosec": 436768787
        }
      }
    },
    {
      "saved_at_unix": 1773361642.9113927,
      "saved_at_iso": "2026-03-13T09:27:22.911393",
      "april_tags": [
        {
          "tag_id": 1,
          "position_m": {
            "x": -0.14579940445120473,
            "y": 0.047345794031974,
            "z": 0.4483082875872645
          },
          "orientation_deg": {
            "roll": 27.103749788936852,
            "pitch": -0.6911149771193272,
            "yaw": -11.713054394922535
          },
          "tracking": true
        }
      ],
      "franka_right_arm": {
        "received": true,
        "receive_count": 51599,
        "arm_id": 0,
        "joint_names": [
          "fr3_joint1",
          "fr3_joint2",
          "fr3_joint3",
          "fr3_joint4",
          "fr3_joint5",
          "fr3_joint6",
          "fr3_joint7"
        ],
        "joint_positions": [
          1.1538971662521362,
          1.3659371137619019,
          -0.6357018351554871,
          -1.3480581045150757,
          1.7796833515167236,
          0.5884261727333069,
          -0.9192275404930115
        ],
        "joint_torques": [
          20.94456672668457,
          -39.88404083251953,
          -1.0016855001449585,
          19.880023956298828,
          2.265475273132324,
          -1.0694047212600708,
          0.07013668864965439
        ],
        "source_topic": "/joint_states",
        "source_stamp": {
          "sec": 1773361642,
          "nanosec": 909525699
        }
      }
    },
    {
      "saved_at_unix": 1773361672.3821769,
      "saved_at_iso": "2026-03-13T09:27:52.382177",
      "april_tags": [
        {
          "tag_id": 1,
          "position_m": {
            "x": -0.20960718276361123,
            "y": 0.07102549573004927,
            "z": 0.4863942297717261
          },
          "orientation_deg": {
            "roll": 20.738616441474534,
            "pitch": 2.887266262707439,
            "yaw": 2.2845490261615913
          },
          "tracking": true
        }
      ],
      "franka_right_arm": {
        "received": true,
        "receive_count": 80882,
        "arm_id": 0,
        "joint_names": [
          "fr3_joint1",
          "fr3_joint2",
          "fr3_joint3",
          "fr3_joint4",
          "fr3_joint5",
          "fr3_joint6",
          "fr3_joint7"
        ],
        "joint_positions": [
          1.0705665349960327,
          1.476511001586914,
          -0.5178170800209045,
          -1.233309268951416,
          1.8581434488296509,
          0.8019499778747559,
          -1.063638687133789
        ],
        "joint_torques": [
          21.52775764465332,
          -43.35541534423828,
          0.9740225672721863,
          20.371967315673828,
          1.9184904098510742,
          -1.1151810884475708,
          0.07013668864965439
        ],
        "source_topic": "/joint_states",
        "source_stamp": {
          "sec": 1773361672,
          "nanosec": 380782921
        }
      }
    },
    {
      "saved_at_unix": 1773361746.6646209,
      "saved_at_iso": "2026-03-13T09:29:06.664621",
      "april_tags": [
        {
          "tag_id": 1,
          "position_m": {
            "x": -0.14087969749673293,
            "y": -0.08372938420541064,
            "z": 0.38044540184105713
          },
          "orientation_deg": {
            "roll": 24.355542741653395,
            "pitch": -8.701304651944097,
            "yaw": 18.46909074168532
          },
          "tracking": true
        }
      ],
      "franka_right_arm": {
        "received": true,
        "receive_count": 154950,
        "arm_id": 0,
        "joint_names": [
          "fr3_joint1",
          "fr3_joint2",
          "fr3_joint3",
          "fr3_joint4",
          "fr3_joint5",
          "fr3_joint6",
          "fr3_joint7"
        ],
        "joint_positions": [
          0.9924885630607605,
          1.2630119323730469,
          -0.43961063027381897,
          -1.081249475479126,
          1.8585413694381714,
          0.8127299547195435,
          -1.0646731853485107
        ],
        "joint_torques": [
          24.03508186340332,
          -39.13025665283203,
          4.231163501739502,
          20.026813507080078,
          1.9111661911010742,
          -0.6326981782913208,
          0.04450192302465439
        ],
        "source_topic": "/joint_states",
        "source_stamp": {
          "sec": 1773361746,
          "nanosec": 662599602
        }
      }
    },
    {
      "saved_at_unix": 1773361769.7694974,
      "saved_at_iso": "2026-03-13T09:29:29.769497",
      "april_tags": [
        {
          "tag_id": 1,
          "position_m": {
            "x": -0.10379276922500486,
            "y": -0.08497954213923076,
            "z": 0.4352700657132526
          },
          "orientation_deg": {
            "roll": 35.2212576241938,
            "pitch": -2.084680949491702,
            "yaw": 13.582006601305036
          },
          "tracking": true
        }
      ],
      "franka_right_arm": {
        "received": true,
        "receive_count": 177985,
        "arm_id": 0,
        "joint_names": [
          "fr3_joint1",
          "fr3_joint2",
          "fr3_joint3",
          "fr3_joint4",
          "fr3_joint5",
          "fr3_joint6",
          "fr3_joint7"
        ],
        "joint_positions": [
          0.9746785759925842,
          1.2624462842941284,
          -0.5847039222717285,
          -1.0852407217025757,
          1.7192376852035522,
          0.7472594976425171,
          -1.0625932216644287
        ],
        "joint_torques": [
          25.63389778137207,
          -37.99958038330078,
          2.410179853439331,
          20.102191925048828,
          1.7445402145385742,
          -0.6391068696975708,
          0.05731930583715439
        ],
        "source_topic": "/joint_states",
        "source_stamp": {
          "sec": 1773361769,
          "nanosec": 768066092
        }
      }
    },
    {
      "saved_at_unix": 1773361838.9162402,
      "saved_at_iso": "2026-03-13T09:30:38.916240",
      "april_tags": [
        {
          "tag_id": 1,
          "position_m": {
            "x": -0.03513159327247218,
            "y": -0.12115473102513731,
            "z": 0.48913331216838135
          },
          "orientation_deg": {
            "roll": 39.65656275490832,
            "pitch": 15.122973831246815,
            "yaw": 0.8032532735486758
          },
          "tracking": true
        }
      ],
      "franka_right_arm": {
        "received": true,
        "receive_count": 246923,
        "arm_id": 0,
        "joint_names": [
          "fr3_joint1",
          "fr3_joint2",
          "fr3_joint3",
          "fr3_joint4",
          "fr3_joint5",
          "fr3_joint6",
          "fr3_joint7"
        ],
        "joint_positions": [
          0.9436565041542053,
          1.2366697788238525,
          -0.7713834047317505,
          -1.053276777267456,
          1.6314804553985596,
          0.6659950613975525,
          -0.7889783978462219
        ],
        "joint_torques": [
          27.91508674621582,
          -35.46051788330078,
          0.5376212000846863,
          19.681659698486328,
          1.9377164840698242,
          -0.3882523775100708,
          0.05731930583715439
        ],
        "source_topic": "/joint_states",
        "source_stamp": {
          "sec": 1773361838,
          "nanosec": 914474088
        }
      }
    },
    {
      "saved_at_unix": 1773361882.8911612,
      "saved_at_iso": "2026-03-13T09:31:22.891161",
      "april_tags": [
        {
          "tag_id": 1,
          "position_m": {
            "x": -0.03242797811340782,
            "y": -0.0917306697973609,
            "z": 0.56709028949545
          },
          "orientation_deg": {
            "roll": 18.494156493369925,
            "pitch": 21.764611097983106,
            "yaw": -6.508895400766515
          },
          "tracking": true
        }
      ],
      "franka_right_arm": {
        "received": true,
        "receive_count": 290646,
        "arm_id": 0,
        "joint_names": [
          "fr3_joint1",
          "fr3_joint2",
          "fr3_joint3",
          "fr3_joint4",
          "fr3_joint5",
          "fr3_joint6",
          "fr3_joint7"
        ],
        "joint_positions": [
          0.9278287291526794,
          1.2335643768310547,
          -0.7714172601699829,
          -1.3177471160888672,
          1.8147776126861572,
          0.7281410098075867,
          -0.6463760733604431
        ],
        "joint_torques": [
          28.29197883605957,
          -35.15900421142578,
          0.4344717860221863,
          20.026813507080078,
          2.051241874694824,
          -1.0025712251663208,
          0.03717770427465439
        ],
        "source_topic": "/joint_states",
        "source_stamp": {
          "sec": 1773361882,
          "nanosec": 890475623
        }
      }
    },
    {
      "saved_at_unix": 1773361907.7966664,
      "saved_at_iso": "2026-03-13T09:31:47.796666",
      "april_tags": [
        {
          "tag_id": 1,
          "position_m": {
            "x": -0.017976116526266628,
            "y": -0.11254800949342783,
            "z": 0.5840420673267877
          },
          "orientation_deg": {
            "roll": 10.261521147911163,
            "pitch": 33.74198713999171,
            "yaw": -19.164460176537773
          },
          "tracking": true
        }
      ],
      "franka_right_arm": {
        "received": true,
        "receive_count": 315492,
        "arm_id": 0,
        "joint_names": [
          "fr3_joint1",
          "fr3_joint2",
          "fr3_joint3",
          "fr3_joint4",
          "fr3_joint5",
          "fr3_joint6",
          "fr3_joint7"
        ],
        "joint_positions": [
          0.9332473278045654,
          1.2154806852340698,
          -0.832109808921814,
          -1.3241446018218994,
          1.8156483173370361,
          0.8263425827026367,
          -0.3914722502231598
        ],
        "joint_torques": [
          28.97831916809082,
          -34.09973907470703,
          -0.3827889561653137,
          20.173603057861328,
          2.205050468444824,
          -0.9632035493850708,
          0.08386959880590439
        ],
        "source_topic": "/joint_states",
        "source_stamp": {
          "sec": 1773361907,
          "nanosec": 796011618
        }
      }
    },
    {
      "saved_at_unix": 1773361961.0411355,
      "saved_at_iso": "2026-03-13T09:32:41.041136",
      "april_tags": [
        {
          "tag_id": 1,
          "position_m": {
            "x": 0.03176149374808354,
            "y": -0.12124646721655305,
            "z": 0.6084533651920518
          },
          "orientation_deg": {
            "roll": 8.727476433303272,
            "pitch": 30.841371293671585,
            "yaw": -18.80380187247573
          },
          "tracking": true
        }
      ],
      "franka_right_arm": {
        "received": true,
        "receive_count": 368645,
        "arm_id": 0,
        "joint_names": [
          "fr3_joint1",
          "fr3_joint2",
          "fr3_joint3",
          "fr3_joint4",
          "fr3_joint5",
          "fr3_joint6",
          "fr3_joint7"
        ],
        "joint_positions": [
          0.8618278503417969,
          1.2017744779586792,
          -0.8615919351577759,
          -1.3187565803527832,
          1.8156893253326416,
          0.7210438847541809,
          -0.39309823513031006
        ],
        "joint_torques": [
          30.04155158996582,
          -33.07221221923828,
          -0.07730801403522491,
          19.927631378173828,
          2.205050468444824,
          -1.0758134126663208,
          0.010627411305904388
        ],
        "source_topic": "/joint_states",
        "source_stamp": {
          "sec": 1773361961,
          "nanosec": 40383265
        }
      }
    },
    {
      "saved_at_unix": 1773361987.7463667,
      "saved_at_iso": "2026-03-13T09:33:07.746367",
      "april_tags": [
        {
          "tag_id": 1,
          "position_m": {
            "x": 0.014780823253520554,
            "y": -0.055463913609637705,
            "z": 0.5278373724005047
          },
          "orientation_deg": {
            "roll": -1.5565141213114644,
            "pitch": 17.55479726433203,
            "yaw": -23.459665462848736
          },
          "tracking": true
        }
      ],
      "franka_right_arm": {
        "received": true,
        "receive_count": 395240,
        "arm_id": 0,
        "joint_names": [
          "fr3_joint1",
          "fr3_joint2",
          "fr3_joint3",
          "fr3_joint4",
          "fr3_joint5",
          "fr3_joint6",
          "fr3_joint7"
        ],
        "joint_positions": [
          1.0931878089904785,
          1.0312803983688354,
          -0.8219118714332581,
          -1.7848819494247437,
          1.9305940866470337,
          0.6645006537437439,
          -0.3979194164276123
        ],
        "joint_torques": [
          24.74522590637207,
          -28.26782989501953,
          1.3072744607925415,
          19.038959503173828,
          1.8049650192260742,
          -1.3861771821975708,
          0.13056150078773499
        ],
        "source_topic": "/joint_states",
        "source_stamp": {
          "sec": 1773361987,
          "nanosec": 745020131
        }
      }
    },
    {
      "saved_at_unix": 1773362020.6526635,
      "saved_at_iso": "2026-03-13T09:33:40.652663",
      "april_tags": [
        {
          "tag_id": 1,
          "position_m": {
            "x": 0.06684216711917507,
            "y": -0.11852727450654328,
            "z": 0.5392403376140994
          },
          "orientation_deg": {
            "roll": 5.29504410712818,
            "pitch": 16.87702323128811,
            "yaw": -13.362458952293274
          },
          "tracking": true
        }
      ],
      "franka_right_arm": {
        "received": true,
        "receive_count": 428074,
        "arm_id": 0,
        "joint_names": [
          "fr3_joint1",
          "fr3_joint2",
          "fr3_joint3",
          "fr3_joint4",
          "fr3_joint5",
          "fr3_joint6",
          "fr3_joint7"
        ],
        "joint_positions": [
          0.9181644916534424,
          1.027744174003601,
          -0.784294843673706,
          -1.5696016550064087,
          1.9264180660247803,
          0.5669229030609131,
          -0.405513197183609
        ],
        "joint_torques": [
          27.93889045715332,
          -29.29932403564453,
          3.231407880783081,
          19.384113311767578,
          1.4176969528198242,
          -1.3138505220413208,
          0.09027829021215439
        ],
        "source_topic": "/joint_states",
        "source_stamp": {
          "sec": 1773362020,
          "nanosec": 651555466
        }
      }
    },
    {
      "saved_at_unix": 1773362049.5913725,
      "saved_at_iso": "2026-03-13T09:34:09.591372",
      "april_tags": [
        {
          "tag_id": 1,
          "position_m": {
            "x": 0.05372285778491609,
            "y": -0.10489007009426424,
            "z": 0.36609476088711423
          },
          "orientation_deg": {
            "roll": 10.529056028850192,
            "pitch": 2.740120568048824,
            "yaw": -11.667083793704863
          },
          "tracking": true
        }
      ],
      "franka_right_arm": {
        "received": true,
        "receive_count": 456912,
        "arm_id": 0,
        "joint_names": [
          "fr3_joint1",
          "fr3_joint2",
          "fr3_joint3",
          "fr3_joint4",
          "fr3_joint5",
          "fr3_joint6",
          "fr3_joint7"
        ],
        "joint_positions": [
          1.2276825904846191,
          0.7888312339782715,
          -0.7785905599594116,
          -1.8273909091949463,
          2.0149481296539307,
          0.5679957866668701,
          -0.42042624950408936
        ],
        "joint_torques": [
          21.19847297668457,
          -21.55518341064453,
          4.258934497833252,
          19.729267120361328,
          1.4845304489135742,
          -1.0620805025100708,
          0.08386959880590439
        ],
        "source_topic": "/joint_states",
        "source_stamp": {
          "sec": 1773362049,
          "nanosec": 590082905
        }
      }
    },
    {
      "saved_at_unix": 1773362083.1639664,
      "saved_at_iso": "2026-03-13T09:34:43.163966",
      "april_tags": [
        {
          "tag_id": 1,
          "position_m": {
            "x": 0.032628132657558345,
            "y": -0.04967003314046052,
            "z": 0.26000289088155026
          },
          "orientation_deg": {
            "roll": 4.025352273645587,
            "pitch": 5.801212711378385,
            "yaw": -8.585421233676126
          },
          "tracking": true
        }
      ],
      "franka_right_arm": {
        "received": true,
        "receive_count": 490384,
        "arm_id": 0,
        "joint_names": [
          "fr3_joint1",
          "fr3_joint2",
          "fr3_joint3",
          "fr3_joint4",
          "fr3_joint5",
          "fr3_joint6",
          "fr3_joint7"
        ],
        "joint_positions": [
          1.500181794166565,
          0.5503088235855103,
          -0.7683104872703552,
          -2.1192736625671387,
          2.0982112884521484,
          0.8411847352981567,
          -0.5107381343841553
        ],
        "joint_torques": [
          14.45805549621582,
          -14.164131164550781,
          5.080162525177002,
          20.125995635986328,
          1.2236051559448242,
          -1.2277909517288208,
          0.08386959880590439
        ],
        "source_topic": "/joint_states",
        "source_stamp": {
          "sec": 1773362083,
          "nanosec": 163298083
        }
      }
    },
    {
      "saved_at_unix": 1773362151.8778846,
      "saved_at_iso": "2026-03-13T09:35:51.877885",
      "april_tags": [
        {
          "tag_id": 1,
          "position_m": {
            "x": 0.06149042964211769,
            "y": -0.07577623596922974,
            "z": 0.34012146040815816
          },
          "orientation_deg": {
            "roll": -1.5795979101387239,
            "pitch": 4.7068940977580755,
            "yaw": -20.676120346977225
          },
          "tracking": true
        }
      ],
      "franka_right_arm": {
        "received": true,
        "receive_count": 558844,
        "arm_id": 0,
        "joint_names": [
          "fr3_joint1",
          "fr3_joint2",
          "fr3_joint3",
          "fr3_joint4",
          "fr3_joint5",
          "fr3_joint6",
          "fr3_joint7"
        ],
        "joint_positions": [
          1.3463495969772339,
          0.6361083388328552,
          -0.7936812043190002,
          -2.0777626037597656,
          2.097363233566284,
          0.694351077079773,
          -0.24974605441093445
        ],
        "joint_torques": [
          17.85405158996582,
          -15.822456359863281,
          5.568138599395752,
          19.606281280517578,
          1.2236051559448242,
          -1.2607499361038208,
          0.07746090739965439
        ],
        "source_topic": "/joint_states",
        "source_stamp": {
          "sec": 1773362151,
          "nanosec": 876914282
        }
      }
    },
    {
      "saved_at_unix": 1773362182.5838363,
      "saved_at_iso": "2026-03-13T09:36:22.583836",
      "april_tags": [
        {
          "tag_id": 1,
          "position_m": {
            "x": -0.07664614210515404,
            "y": -0.013783644673798261,
            "z": 0.5026357379409238
          },
          "orientation_deg": {
            "roll": -5.260439873889606,
            "pitch": 14.140015565713773,
            "yaw": -8.689633909703513
          },
          "tracking": true
        }
      ],
      "franka_right_arm": {
        "received": true,
        "receive_count": 589444,
        "arm_id": 0,
        "joint_names": [
          "fr3_joint1",
          "fr3_joint2",
          "fr3_joint3",
          "fr3_joint4",
          "fr3_joint5",
          "fr3_joint6",
          "fr3_joint7"
        ],
        "joint_positions": [
          1.1504195928573608,
          1.1155086755752563,
          -0.675763726234436,
          -1.8038780689239502,
          2.163317918777466,
          0.7642794251441956,
          -0.6379038095474243
        ],
        "joint_torques": [
          21.70628547668457,
          -31.86219024658203,
          0.6923453211784363,
          19.237323760986328,
          1.2702970504760742,
          -1.5912553071975708,
          0.05091061443090439
        ],
        "source_topic": "/joint_states",
        "source_stamp": {
          "sec": 1773362182,
          "nanosec": 582553011
        }
      }
    },
    {
      "saved_at_unix": 1773362215.0916827,
      "saved_at_iso": "2026-03-13T09:36:55.091683",
      "april_tags": [
        {
          "tag_id": 1,
          "position_m": {
            "x": 0.17149747555394965,
            "y": -0.12753765175790052,
            "z": 0.6412749825079049
          },
          "orientation_deg": {
            "roll": 5.457378832446791,
            "pitch": 24.44434365093383,
            "yaw": 3.400033042743693
          },
          "tracking": true
        }
      ],
      "franka_right_arm": {
        "received": true,
        "receive_count": 621868,
        "arm_id": 0,
        "joint_names": [
          "fr3_joint1",
          "fr3_joint2",
          "fr3_joint3",
          "fr3_joint4",
          "fr3_joint5",
          "fr3_joint6",
          "fr3_joint7"
        ],
        "joint_positions": [
          0.7673556208610535,
          1.1173994541168213,
          -0.9872088432312012,
          -1.476158857345581,
          1.9511858224868774,
          0.4727332592010498,
          -0.6278718113899231
        ],
        "joint_torques": [
          31.43803596496582,
          -28.92243194580078,
          -0.4343636631965637,
          19.114337921142578,
          1.3774137496948242,
          -1.3001176118850708,
          0.10401120036840439
        ],
        "source_topic": "/joint_states",
        "source_stamp": {
          "sec": 1773362215,
          "nanosec": 90292844
        }
      }
    },
    {
      "saved_at_unix": 1773362247.6303668,
      "saved_at_iso": "2026-03-13T09:37:27.630367",
      "april_tags": [
        {
          "tag_id": 1,
          "position_m": {
            "x": 0.14730195564574805,
            "y": -0.17521465873079461,
            "z": 0.632384225834252
          },
          "orientation_deg": {
            "roll": 1.8823661249219406,
            "pitch": -1.8377150954315062,
            "yaw": 19.250586559401345
          },
          "tracking": true
        }
      ],
      "franka_right_arm": {
        "received": true,
        "receive_count": 654325,
        "arm_id": 0,
        "joint_names": [
          "fr3_joint1",
          "fr3_joint2",
          "fr3_joint3",
          "fr3_joint4",
          "fr3_joint5",
          "fr3_joint6",
          "fr3_joint7"
        ],
        "joint_positions": [
          0.3924744427204132,
          1.0970836877822876,
          -0.32812491059303284,
          -1.213121771812439,
          1.9752709865570068,
          0.5327301025390625,
          -0.629177987575531
        ],
        "joint_torques": [
          33.81840515136719,
          -35.35736846923828,
          11.49129581451416,
          17.686115264892578,
          0.7832365036010742,
          -1.0620805025100708,
          0.13697019219398499
        ],
        "source_topic": "/joint_states",
        "source_stamp": {
          "sec": 1773362247,
          "nanosec": 629017611
        }
      }
    },
    {
      "saved_at_unix": 1773362277.5379775,
      "saved_at_iso": "2026-03-13T09:37:57.537977",
      "april_tags": [
        {
          "tag_id": 1,
          "position_m": {
            "x": 0.015545512865776604,
            "y": -0.14585754572951148,
            "z": 0.5106279439640082
          },
          "orientation_deg": {
            "roll": 14.44282681515936,
            "pitch": 29.22990884189966,
            "yaw": 0.2882494724903201
          },
          "tracking": true
        }
      ],
      "franka_right_arm": {
        "received": true,
        "receive_count": 684122,
        "arm_id": 0,
        "joint_names": [
          "fr3_joint1",
          "fr3_joint2",
          "fr3_joint3",
          "fr3_joint4",
          "fr3_joint5",
          "fr3_joint6",
          "fr3_joint7"
        ],
        "joint_positions": [
          0.9066954255104065,
          0.9511558413505554,
          -0.6505724191665649,
          -1.4758358001708984,
          1.7229535579681396,
          0.9591841101646423,
          -0.6119445562362671
        ],
        "joint_torques": [
          27.96269416809082,
          -29.32312774658203,
          5.873619556427002,
          20.173603057861328,
          1.4442472457885742,
          -1.0163041353225708,
          0.09027829021215439
        ],
        "source_topic": "/joint_states",
        "source_stamp": {
          "sec": 1773362277,
          "nanosec": 537051724
        }
      }
    },
    {
      "saved_at_unix": 1773362298.5738318,
      "saved_at_iso": "2026-03-13T09:38:18.573832",
      "april_tags": [
        {
          "tag_id": 1,
          "position_m": {
            "x": -0.001592826667995519,
            "y": -0.07362907748221473,
            "z": 0.5480173756822653
          },
          "orientation_deg": {
            "roll": -7.534821394886889,
            "pitch": 12.453544619497338,
            "yaw": -2.1157960499085617
          },
          "tracking": true
        }
      ],
      "franka_right_arm": {
        "received": true,
        "receive_count": 705096,
        "arm_id": 0,
        "joint_names": [
          "fr3_joint1",
          "fr3_joint2",
          "fr3_joint3",
          "fr3_joint4",
          "fr3_joint5",
          "fr3_joint6",
          "fr3_joint7"
        ],
        "joint_positions": [
          0.8656905293464661,
          0.9981502890586853,
          -0.5490447878837585,
          -1.7315735816955566,
          2.0180962085723877,
          0.7783762812614441,
          -0.6521426439285278
        ],
        "joint_torques": [
          26.18931770324707,
          -31.06079864501953,
          7.182823657989502,
          18.523212432861328,
          0.9965543746948242,
          -1.6699906587600708,
          0.11682858318090439
        ],
        "source_topic": "/joint_states",
        "source_stamp": {
          "sec": 1773362298,
          "nanosec": 572529792
        }
      }
    },
    {
      "saved_at_unix": 1773362321.4787638,
      "saved_at_iso": "2026-03-13T09:38:41.478764",
      "april_tags": [
        {
          "tag_id": 1,
          "position_m": {
            "x": -0.14341658060844517,
            "y": -0.025722482126461922,
            "z": 0.5399215658504621
          },
          "orientation_deg": {
            "roll": -10.673967310772985,
            "pitch": 2.2896527147752757,
            "yaw": -17.12031282651715
          },
          "tracking": true
        }
      ],
      "franka_right_arm": {
        "received": true,
        "receive_count": 727923,
        "arm_id": 0,
        "joint_names": [
          "fr3_joint1",
          "fr3_joint2",
          "fr3_joint3",
          "fr3_joint4",
          "fr3_joint5",
          "fr3_joint6",
          "fr3_joint7"
        ],
        "joint_positions": [
          0.7932284474372864,
          1.292765498161316,
          -0.2942686080932617,
          -1.4120835065841675,
          2.059793710708618,
          0.8996734619140625,
          -0.44558998942375183
        ],
        "joint_torques": [
          25.86003303527832,
          -39.45557403564453,
          9.03157901763916,
          18.868366241455078,
          0.8702116012573242,
          -1.6104813814163208,
          0.05731930583715439
        ],
        "source_topic": "/joint_states",
        "source_stamp": {
          "sec": 1773362321,
          "nanosec": 477075653
        }
      }
    }
  ],
  "merged_from": [
    "nse-3324154235759263547-apriltag_franka_snapshots_20260313_092523.json.json",
    "nse-7520524931648433387-apriltag_franka_snapshots_20260313_093844.json.json"
  ],
  "source_snapshot_counts": {
    "nse-3324154235759263547-apriltag_franka_snapshots_20260313_092523.json.json": 11,
    "nse-7520524931648433387-apriltag_franka_snapshots_20260313_093844.json.json": 20
  }
}
